odoo/addons/energy_communities/__init__.py
odoo/addons/energy_communities/__manifest__.py
odoo/addons/energy_communities/hooks.py
odoo/addons/energy_communities/utils.py
odoo/addons/energy_communities/_services/__init__.py
odoo/addons/energy_communities/_services/ce_community_service.py
odoo/addons/energy_communities/_services/ce_landing_service.py
odoo/addons/energy_communities/_services/ce_member_profile_service.py
odoo/addons/energy_communities/_services/ce_member_service.py
odoo/addons/energy_communities/_services/schemas.py
odoo/addons/energy_communities/client_map/__init__.py
odoo/addons/energy_communities/client_map/config.py
odoo/addons/energy_communities/client_map/resources/landing_cmplace.py
odoo/addons/energy_communities/components/__init__.py
odoo/addons/energy_communities/components/collections.py
odoo/addons/energy_communities/components/contract_utils.py
odoo/addons/energy_communities/components/sale_order_utils.py
odoo/addons/energy_communities/components/user_creator.py
odoo/addons/energy_communities/controllers/__init__.py
odoo/addons/energy_communities/controllers/_controllers.py
odoo/addons/energy_communities/controllers/controllers.py
odoo/addons/energy_communities/controllers/website_community_data.py
odoo/addons/energy_communities/controllers/website_form_controllers.py
odoo/addons/energy_communities/controllers/website_subscription_main.py
odoo/addons/energy_communities/controllers/website_subscription_voluntary_share.py
odoo/addons/energy_communities/data/auth_oauth_provider_data.xml
odoo/addons/energy_communities/data/community_maps_data.xml
odoo/addons/energy_communities/data/crm_lead_tag.xml
odoo/addons/energy_communities/data/energy_action.xml
odoo/addons/energy_communities/data/ir_cron.xml
odoo/addons/energy_communities/data/mail_template_data.xml
odoo/addons/energy_communities/data/mail_template_update_data.xml
odoo/addons/energy_communities/data/mail_templates_email_layouts.xml
odoo/addons/energy_communities/data/product_data.xml
energy_communities-16.0.0.2.0.dist-info/METADATA
energy_communities-16.0.0.2.0.dist-info/WHEEL
energy_communities-16.0.0.2.0.dist-info/top_level.txt
energy_communities-16.0.0.2.0.dist-info/RECORD
