Metadata-Version: 2.1
Name: energy-communities
Version: 16.0.0.2.0
Summary: Energy Community
Home-page: https://coopdevs.org
Author: Coopdevs Treball SCCL & Som Energia SCCL
License: AGPL-3
Classifier: Programming Language :: Python
Classifier: Framework :: Odoo
Classifier: Framework :: Odoo :: 16.0
Classifier: License :: OSI Approved :: GNU Affero General Public License v3
Requires-Python: >=3.10
Requires-Dist: odoo-addon-account-banking-mandate <16.1dev,>=16.0dev
Requires-Dist: odoo-addon-account-lock-date-update <16.1dev,>=16.0dev
Requires-Dist: odoo-addon-account-multicompany-easy-creation <16.1dev,>=16.0dev
Requires-Dist: odoo-addon-account-payment-order <16.1dev,>=16.0dev
Requires-Dist: odoo-addon-account-reconcile-oca <16.1dev,>=16.0dev
Requires-Dist: odoo-addon-auth-api-key <16.1dev,>=16.0dev
Requires-Dist: odoo-addon-auth-oidc <16.1dev,>=16.0dev
Requires-Dist: odoo-addon-base-rest <16.1dev,>=16.0dev
Requires-Dist: odoo-addon-base-technical-features <16.1dev,>=16.0dev
Requires-Dist: odoo-addon-base-user-role <16.1dev,>=16.0dev
Requires-Dist: odoo-addon-base-user-role-company <16.1dev,>=16.0dev
Requires-Dist: odoo-addon-community-maps <16.1dev,>=16.0dev
Requires-Dist: odoo-addon-l10n-es-aeat <16.1dev,>=16.0dev
Requires-Dist: odoo-addon-l10n-es-aeat-sii-oca <16.1dev,>=16.0dev
Requires-Dist: odoo-addon-mail-multicompany <16.1dev,>=16.0dev
Requires-Dist: odoo-addon-metadata <16.1dev,>=16.0dev
Requires-Dist: odoo-addon-partner-firstname <16.1dev,>=16.0dev
Requires-Dist: odoo-addon-partner-multi-company <16.1dev,>=16.0dev
Requires-Dist: odoo-addon-queue-job <16.1dev,>=16.0dev
Requires-Dist: odoo <16.1dev,>=16.0a
